CHANGES.txt
MANIFEST.in
README.md
requirements-test.txt
requirements.txt
setup.cfg
setup.py
howdou/__init__.py
howdou/howdou.py
howdou/tests.py
howdou.egg-info/PKG-INFO
howdou.egg-info/SOURCES.txt
howdou.egg-info/dependency_links.txt
howdou.egg-info/entry_points.txt
howdou.egg-info/requires.txt
howdou.egg-info/top_level.txt