Metadata-Version: 1.1
Name: howdou
Version: 3.0.6
Summary: Instant coding answers via the command line
Home-page: https://github.com/chrisspen/howdou
Author: Chris Spencer
Author-email: chrisspen@gmail.com
License: MIT
Keywords: howdou help console command line answer
Platform: UNKNOWN
Classifier: Development Status :: 5 - Production/Stable
Classifier: Environment :: Console
Classifier: Intended Audience :: Developers
Classifier: Programming Language :: Python :: 2
Classifier: Programming Language :: Python :: 2.6
Classifier: Programming Language :: Python :: 2.7
Classifier: Topic :: Documentation
